pygments_pre_commit.py
pygments_pre_commit-2.3.0.dist-info/LICENSE
pygments_pre_commit-2.3.0.dist-info/METADATA
pygments_pre_commit-2.3.0.dist-info/WHEEL
pygments_pre_commit-2.3.0.dist-info/entry_points.txt
pygments_pre_commit-2.3.0.dist-info/top_level.txt
pygments_pre_commit-2.3.0.dist-info/RECORD
