Metadata-Version: 2.1
Name: pygments-pre-commit
Version: 2.3.0
Summary: A pygments lexer for pre-commit output.
Home-page: https://github.com/asottile/pygments-pre-commit
Author: Anthony Sottile
Author-email: asottile@umich.edu
License: MIT
Classifier: License :: OSI Approved :: MIT License
Classifier: Programming Language :: Python :: 3
Classifier: Programming Language :: Python :: 3 :: Only
Classifier: Programming Language :: Python :: Implementation :: CPython
Classifier: Programming Language :: Python :: Implementation :: PyPy
Requires-Python: >=3.8
License-File: LICENSE
Requires-Dist: pygments
